ai_observability/__init__.py
ai_observability-0.0.1.dist-info/METADATA
ai_observability-0.0.1.dist-info/WHEEL
ai_observability-0.0.1.dist-info/RECORD
